snanpy/__init__.py
snanpy/functions.py
snanpy-2.6.0.dist-info/licenses/LICENSE.txt
snanpy-2.6.0.dist-info/METADATA
snanpy-2.6.0.dist-info/WHEEL
snanpy-2.6.0.dist-info/top_level.txt
snanpy-2.6.0.dist-info/RECORD
