Metadata-Version: 2.4
Name: snanpy
Version: 2.6.0
Author-email: Antonius Tilgner <antonius.tilgner@proton.me>
License-File: LICENSE.txt
Requires-Dist: matplotlib
Dynamic: license-file
